pyvalidly/__init__.py
pyvalidly/core.py
pyvalidly/exceptions.py
pyvalidly/schema.py
pyvalidly/validations.py
pyvalidly-1.0.1.dist-info/licenses/LICENSE
pyvalidly-1.0.1.dist-info/METADATA
pyvalidly-1.0.1.dist-info/WHEEL
pyvalidly-1.0.1.dist-info/top_level.txt
pyvalidly-1.0.1.dist-info/RECORD
