Metadata-Version: 2.4
Name: pyvalidly
Version: 1.0.1
Summary: Lightweight, zero-dependency Python library for validating dictionaries with optional coercion and custom rules
Author-email: Deepak singh <deepaksingh20899@gmail.com>
License: MIT License
Project-URL: Repository, https://github.com/dark00infinity/pyvalidly
Keywords: validation,schema,dict,type-checking,pydantic-alternative
Classifier: Programming Language :: Python :: 3
Classifier: License :: OSI Approved :: MIT License
Classifier: Operating System :: OS Independent
Classifier: Intended Audience :: Developers
Classifier: Topic :: Software Development :: Libraries :: Python Modules
Requires-Python: >=3.7
License-File: LICENSE
Dynamic: license-file
